lunatone_rest_api_client/__init__.py
lunatone_rest_api_client/auth.py
lunatone_rest_api_client/base.py
lunatone_rest_api_client/dali.py
lunatone_rest_api_client/devices.py
lunatone_rest_api_client/discovery.py
lunatone_rest_api_client/info.py
lunatone_rest_api_client/sensors.py
lunatone_rest_api_client/zones.py
lunatone_rest_api_client/models/__init__.py
lunatone_rest_api_client/models/common.py
lunatone_rest_api_client/models/control.py
lunatone_rest_api_client/models/dali.py
lunatone_rest_api_client/models/devices.py
lunatone_rest_api_client/models/info.py
lunatone_rest_api_client/models/sensors.py
lunatone_rest_api_client/models/zones.py
lunatone_rest_api_client-0.5.7.dist-info/METADATA
lunatone_rest_api_client-0.5.7.dist-info/WHEEL
lunatone_rest_api_client-0.5.7.dist-info/licenses/LICENSE
lunatone_rest_api_client-0.5.7.dist-info/RECORD
