Metadata-Version: 2.4
Name: lunatone-rest-api-client
Version: 0.5.7
Summary: A client library for accessing the Lunatone REST API
Project-URL: Homepage, https://www.lunatone.com
Project-URL: Source, https://gitlab.com/lunatone-public/lunatone-rest-api-client
Project-URL: Issues, https://gitlab.com/lunatone-public/lunatone-rest-api-client/-/issues
Author-email: David Bugl <bugl@lunatone.com>
License-Expression: GPL-3.0-only
License-File: LICENSE
Keywords: api,client,lunatone
Requires-Python: >=3.12
Requires-Dist: aiohttp[speedups]>=3.12.14
Requires-Dist: pydantic>=2.11.7
